myprojectpythonreda/__init__.py
myprojectpythonreda/myprojectpythonReda.py
myprojectpythonreda-0.1.1.dist-info/LICENSE
myprojectpythonreda-0.1.1.dist-info/METADATA
myprojectpythonreda-0.1.1.dist-info/WHEEL
myprojectpythonreda-0.1.1.dist-info/RECORD
