Metadata-Version: 2.3
Name: myprojectpythonReda
Version: 0.1.1
Summary: package for the python project 2025 class
License: MIT
Author: Reda El Fassi
Requires-Python: >=3.12,<4.0
Classifier: License :: OSI Approved :: MIT License
Classifier: Programming Language :: Python :: 3
Classifier: Programming Language :: Python :: 3.12
Classifier: Programming Language :: Python :: 3.13
Requires-Dist: pybacktestchain (>=0.2.1,<0.3.0)
